ask_robot/__init__.py
ask_robot/__version__.py
ask_robot/calculate.py
ask_robot/chatgpt.py
ask_robot/config.py
ask_robot/first_message.py
ask_robot/invalid_today_in_history.py
ask_robot/local.py
ask_robot/logger.py
ask_robot/main.py
ask_robot/main_backup.py
ask_robot/msg_handle.py
ask_robot/news_60s.py
ask_robot/recv_msg.py
ask_robot/sina_news.py
ask_robot/translate.py
ask_robot-0.0.4.dist-info/entry_points.txt
ask_robot-0.0.4.dist-info/LICENSE
ask_robot-0.0.4.dist-info/WHEEL
ask_robot-0.0.4.dist-info/METADATA
ask_robot-0.0.4.dist-info/RECORD
