Metadata-Version: 2.1
Name: ask-robot
Version: 0.0.4
Summary: the robot for chat system
License: MIT
Author: idlewith
Author-email: newellzhou@163.com
Requires-Python: >=3.7.1,<4.0.0
Classifier: License :: OSI Approved :: MIT License
Classifier: Programming Language :: Python :: 3
Classifier: Programming Language :: Python :: 3.8
Classifier: Programming Language :: Python :: 3.9
Classifier: Programming Language :: Python :: 3.10
Requires-Dist: Flask (>=2.2.3,<3.0.0)
Requires-Dist: bs4 (>=0.0.1,<0.0.2)
Requires-Dist: cryptography (>=39.0.2,<40.0.0)
Requires-Dist: openai (>=0.27.2,<0.28.0)
Requires-Dist: requests (>=2.28.2,<3.0.0)
Requires-Dist: wechatpy (>=1.8.18,<2.0.0)
